{
	"hooks": [
		{
            "name": "dw.order.calculate",
            "script": "./hooks/cart/calculate.js"
        },
        {
            "name": "dw.order.calculateKatapult",
            "script": "./hooks/cart/calculateKatapult.js"
        },
        {
            "name": "dw.order.calculateShipping",
            "script": "./hooks/cart/calculate.js"
        },
        {
            "name": "dw.order.calculateTaxKatapult",
            "script": "./hooks/cart/calculateKatapult.js"
        },
        {
            "name": "dw.order.calculateTax",
            "script": "./hooks/cart/calculate.js"
        },
		{
			"name": "app.payment.form.processor.katapult",
			"script": "./hooks/payment/processor/katapult_form_processor"
		},
		{
			"name": "app.payment.processor.katapult",
			"script": "./hooks/payment/processor/katapult"
		}
	]
}
